.gitignore
.gitlab-ci.yml
LICENSE.txt
MANIFEST.in
README.rst
VERSION
aws_lambda_logging.py
requirements-tests.txt
setup.cfg
setup.py
test_aws_lambda_logging.py
aws_lambda_logging.egg-info/PKG-INFO
aws_lambda_logging.egg-info/SOURCES.txt
aws_lambda_logging.egg-info/dependency_links.txt
aws_lambda_logging.egg-info/top_level.txt