Metadata-Version: 1.0
Name: aws-lambda-logging
Version: 0.0.17
Summary: Nanolib to enhance logging in aws lambda
Home-page: https://gitlab.com/hadr/aws_lambda_logging
Author: UNKNOWN
Author-email: UNKNOWN
License: MIT
Platform: UNKNOWN
